odoo/addons/project_stock_analytic_tag/README.rst
odoo/addons/project_stock_analytic_tag/__init__.py
odoo/addons/project_stock_analytic_tag/__manifest__.py
odoo/addons/project_stock_analytic_tag/i18n/es.po
odoo/addons/project_stock_analytic_tag/i18n/it.po
odoo/addons/project_stock_analytic_tag/i18n/project_stock_analytic_tag.pot
odoo/addons/project_stock_analytic_tag/i18n/pt_BR.po
odoo/addons/project_stock_analytic_tag/models/__init__.py
odoo/addons/project_stock_analytic_tag/models/project_task.py
odoo/addons/project_stock_analytic_tag/models/stock_move.py
odoo/addons/project_stock_analytic_tag/readme/CONTRIBUTORS.rst
odoo/addons/project_stock_analytic_tag/readme/DESCRIPTION.rst
odoo/addons/project_stock_analytic_tag/static/description/icon.png
odoo/addons/project_stock_analytic_tag/static/description/index.html
odoo/addons/project_stock_analytic_tag/tests/__init__.py
odoo/addons/project_stock_analytic_tag/tests/test_project_stock_analytic_tag.py
odoo/addons/project_stock_analytic_tag/views/project_task_view.xml
odoo_addon_project_stock_analytic_tag-16.0.1.0.0.6.dist-info/METADATA
odoo_addon_project_stock_analytic_tag-16.0.1.0.0.6.dist-info/WHEEL
odoo_addon_project_stock_analytic_tag-16.0.1.0.0.6.dist-info/top_level.txt
odoo_addon_project_stock_analytic_tag-16.0.1.0.0.6.dist-info/RECORD
